[{"name": "Dexter", "weight": 3}, {"name": "Vikings", "weight": 1}, {"name": "The Big Bang Theory", "weight": 2}, {"name": "Homeland", "weight": 2}, {"name": "Fargo", "weight": 1}, {"name": "Mad Men", "weight": 1}, {"name": "Battlestar Galactica", "weight": 1}, {"name": "Spartacus: Blood and Sand", "weight": 1}, {"name": "Boardwalk Empire", "weight": 1}, {"name": "Game of Thrones", "weight": 2}, {"name": "Six Feet Under", "weight": 1}, {"name": "Deadwood", "weight": 1}, {"name": "True Detective", "weight": 3}, {"name": "Lost", "weight": 2}, {"name": "Prison Break", "weight": 2}, {"name": "House of Cards", "weight": 2}, {"name": "Oz", "weight": 1}, {"name": "Arrow", "weight": 1}, {"name": "The Walking Dead", "weight": 2}, {"name": "The Shield", "weight": 1}, {"name": "The Wire", "weight": 1}, {"name": "Sherlock", "weight": 2}, {"name": "Breaking Bad", "weight": 3}, {"name": "The Sopranos", "weight": 1}, {"name": "Better Call Saul", "weight": 1}]